SakaiPy/SakaiPy.py
SakaiPy/SakaiSession.py
SakaiPy/__init__.py
SakaiPy/SakaiTools/Announcement.py
SakaiPy/SakaiTools/Assignment.py
SakaiPy/SakaiTools/Calendar.py
SakaiPy/SakaiTools/Forums.py
SakaiPy/SakaiTools/Gradebook.py
SakaiPy/SakaiTools/MyWorkspace.py
SakaiPy/SakaiTools/News.py
SakaiPy/SakaiTools/WebContent.py
SakaiPy/SakaiTools/__init__.py
SakaiPy-2.2.1.dist-info/DESCRIPTION.rst
SakaiPy-2.2.1.dist-info/METADATA
SakaiPy-2.2.1.dist-info/RECORD
SakaiPy-2.2.1.dist-info/WHEEL
SakaiPy-2.2.1.dist-info/metadata.json
SakaiPy-2.2.1.dist-info/top_level.txt
